biobb_amber/__init__.py
biobb_amber/py.typed
biobb_amber/ambpdb/__init__.py
biobb_amber/ambpdb/amber_to_pdb.py
biobb_amber/ambpdb/common.py
biobb_amber/cphstats/__init__.py
biobb_amber/cphstats/cestats_run.py
biobb_amber/cphstats/common.py
biobb_amber/cphstats/cphstats_run.py
biobb_amber/cpptraj/__init__.py
biobb_amber/cpptraj/common.py
biobb_amber/cpptraj/cpptraj_randomize_ions.py
biobb_amber/leap/__init__.py
biobb_amber/leap/common.py
biobb_amber/leap/leap_add_ions.py
biobb_amber/leap/leap_build_linear_structure.py
biobb_amber/leap/leap_gen_top.py
biobb_amber/leap/leap_solvate.py
biobb_amber/parmed/__init__.py
biobb_amber/parmed/common.py
biobb_amber/parmed/parmed_cpinutil.py
biobb_amber/parmed/parmed_hmassrepartition.py
biobb_amber/pdb4amber/__init__.py
biobb_amber/pdb4amber/common.py
biobb_amber/pdb4amber/pdb4amber_run.py
biobb_amber/pmemd/__init__.py
biobb_amber/pmemd/common.py
biobb_amber/pmemd/pmemd_mdrun.py
biobb_amber/process/__init__.py
biobb_amber/process/common.py
biobb_amber/process/process_mdout.py
biobb_amber/process/process_minout.py
biobb_amber/sander/__init__.py
biobb_amber/sander/common.py
biobb_amber/sander/sander_mdrun.py
biobb_amber-5.2.0.dist-info/licenses/LICENSE
biobb_amber-5.2.0.dist-info/METADATA
biobb_amber-5.2.0.dist-info/WHEEL
biobb_amber-5.2.0.dist-info/entry_points.txt
biobb_amber-5.2.0.dist-info/top_level.txt
biobb_amber-5.2.0.dist-info/RECORD
