Metadata-Version: 2.4
Name: biobb_amber
Version: 5.2.0
Summary: Biobb_amber is a BioBB category for AMBER MD package.
Home-page: https://github.com/bioexcel/biobb_amber
Author: Biobb developers
Author-email: adam.hospital@irbbarcelona.org
Project-URL: Documentation, http://biobb-amber.readthedocs.io/en/latest/
Project-URL: Bioexcel, https://bioexcel.eu/
Keywords: Bioinformatics Workflows BioExcel Compatibility MD Amber
Classifier: Development Status :: 5 - Production/Stable
Classifier: Programming Language :: Python :: 3.10
Classifier: License :: OSI Approved :: Apache Software License
Classifier: Operating System :: MacOS :: MacOS X
Classifier: Operating System :: POSIX
Classifier: Operating System :: Unix
Requires-Python: >=3.10
License-File: LICENSE
Requires-Dist: biobb_common==5.2.0
Dynamic: author
Dynamic: author-email
Dynamic: classifier
Dynamic: description
Dynamic: description-content-type
Dynamic: home-page
Dynamic: keywords
Dynamic: license-file
Dynamic: project-url
Dynamic: requires-dist
Dynamic: requires-python
Dynamic: summary
